piccolo/__init__.py
piccolo/custom_types.py
piccolo/main.py
piccolo/py.typed
piccolo/querystring.py
piccolo/schema.py
piccolo/table.py
piccolo/table_reflection.py
piccolo/apps/__init__.py
piccolo/apps/app/__init__.py
piccolo/apps/app/piccolo_app.py
piccolo/apps/app/commands/__init__.py
piccolo/apps/app/commands/new.py
piccolo/apps/app/commands/show_all.py
piccolo/apps/app/commands/templates/piccolo_app.py.jinja
piccolo/apps/app/commands/templates/tables.py.jinja
piccolo/apps/asgi/__init__.py
piccolo/apps/asgi/piccolo_app.py
piccolo/apps/asgi/commands/__init__.py
piccolo/apps/asgi/commands/new.py
piccolo/apps/asgi/commands/templates/app/README.md.jinja
piccolo/apps/asgi/commands/templates/app/_blacksheep_app.py.jinja
piccolo/apps/asgi/commands/templates/app/_esmerald_app.py.jinja
piccolo/apps/asgi/commands/templates/app/_falcon_app.py.jinja
piccolo/apps/asgi/commands/templates/app/_fastapi_app.py.jinja
piccolo/apps/asgi/commands/templates/app/_lilya_app.py.jinja
piccolo/apps/asgi/commands/templates/app/_litestar_app.py.jinja
piccolo/apps/asgi/commands/templates/app/_quart_app.py.jinja
piccolo/apps/asgi/commands/templates/app/_sanic_app.py.jinja
piccolo/apps/asgi/commands/templates/app/_starlette_app.py.jinja
piccolo/apps/asgi/commands/templates/app/app.py.jinja
piccolo/apps/asgi/commands/templates/app/conftest.py.jinja
piccolo/apps/asgi/commands/templates/app/main.py.jinja
piccolo/apps/asgi/commands/templates/app/piccolo_conf.py.jinja
piccolo/apps/asgi/commands/templates/app/piccolo_conf_test.py.jinja
piccolo/apps/asgi/commands/templates/app/requirements.txt.jinja
piccolo/apps/asgi/commands/templates/app/home/__init__.py.jinja
piccolo/apps/asgi/commands/templates/app/home/_blacksheep_endpoints.py.jinja
piccolo/apps/asgi/commands/templates/app/home/_esmerald_endpoints.py.jinja
piccolo/apps/asgi/commands/templates/app/home/_falcon_endpoints.py.jinja
piccolo/apps/asgi/commands/templates/app/home/_lilya_endpoints.py.jinja
piccolo-1.30.0.dist-info/licenses/LICENSE
piccolo-1.30.0.dist-info/METADATA
piccolo-1.30.0.dist-info/WHEEL
piccolo-1.30.0.dist-info/entry_points.txt
piccolo-1.30.0.dist-info/top_level.txt
piccolo-1.30.0.dist-info/RECORD
