Metadata-Version: 2.4
Name: piccolo
Version: 1.30.0
Summary: A fast, user friendly ORM and query builder which supports asyncio.
Home-page: https://github.com/piccolo-orm/piccolo
Author: Daniel Townsend
Author-email: dan@dantownsend.co.uk
License: MIT
Project-URL: Documentation, https://piccolo-orm.readthedocs.io/en/latest/index.html
Project-URL: Source, https://github.com/piccolo-orm/piccolo
Project-URL: Tracker, https://github.com/piccolo-orm/piccolo/issues
Classifier: License :: OSI Approved :: MIT License
Classifier: Programming Language :: Python
Classifier: Programming Language :: Python :: 3
Classifier: Programming Language :: Python :: 3.10
Classifier: Programming Language :: Python :: 3.11
Classifier: Programming Language :: Python :: 3.12
Classifier: Programming Language :: Python :: 3.13
Classifier: Programming Language :: Python :: 3.14
Classifier: Programming Language :: Python :: Implementation :: CPython
Classifier: Framework :: AsyncIO
Classifier: Typing :: Typed
Classifier: Topic :: Database
Requires-Python: >=3.10.0
License-File: LICENSE
Requires-Dist: black
Requires-Dist: colorama>=0.4.0
Requires-Dist: Jinja2>=2.11.0
Requires-Dist: targ>=0.3.7
Requires-Dist: inflection>=0.5.1
Requires-Dist: typing-extensions>=4.3.0
Requires-Dist: pydantic[email]==2.*
Provides-Extra: orjson
Requires-Dist: orjson>=3.5.1; extra == "orjson"
Provides-Extra: playground
Requires-Dist: ipython; extra == "playground"
Provides-Extra: postgres
Requires-Dist: asyncpg>=0.30.0; extra == "postgres"
Provides-Extra: sqlite
Requires-Dist: aiosqlite>=0.16.0; extra == "sqlite"
Provides-Extra: uvloop
Requires-Dist: uvloop>=0.12.0; sys_platform != "win32" and extra == "uvloop"
Provides-Extra: all
Requires-Dist: orjson>=3.5.1; extra == "all"
Requires-Dist: ipython; extra == "all"
Requires-Dist: asyncpg>=0.30.0; extra == "all"
Requires-Dist: aiosqlite>=0.16.0; extra == "all"
Requires-Dist: uvloop>=0.12.0; sys_platform != "win32" and extra == "all"
Dynamic: author
Dynamic: author-email
Dynamic: classifier
Dynamic: description
Dynamic: description-content-type
Dynamic: home-page
Dynamic: license
Dynamic: license-file
Dynamic: project-url
Dynamic: provides-extra
Dynamic: requires-dist
Dynamic: requires-python
Dynamic: summary
